{
  "bp-header" : {
    "owner" : "bp.dfs",
    "total_votes" : "4803129209476672512.00000000000000000",
    "producer_key" : "EOS7u2ARuKEDN2ybqSNY5S2cuoLZ6jFBT3BjU5g8SdHsU8kyEESso",
    "is_active" : 1,
    "url" : "https://defis.network",
    "unpaid_blocks" : 0,
    "last_claim_time" : "2020-12-05T09:59:16.000",
    "location" : 702,
    "prepared-url" : "https://defis.network"
  },
  "bp-json-summary" : {
    "url" : "https://defis.network/bp.json",
    "logo" : "https://cdn.jsdelivr.net/gh/defis-net/material/logo/32_32.png",
    "code_of_conduct" : "https://bihu.com/article/1649323677"
  },
  "analyzed-urls" : {
    "duplicate-urls" : null,
    "social-links" : [ ],
    "popularity-boosters" : [ ]
  },
  "p-ram-amounts" : [ ],
  "vote-percentage" : 0.02361599788929993,
  "scoring" : {
    "comp" : [ {
      "score" : "positive",
      "mood" : "good",
      "title" : "web",
      "url" : "https://defis.network"
    }, {
      "score" : "positive",
      "mood" : "good",
      "title" : "bp-json",
      "url" : "https://defis.network/bp.json"
    }, {
      "score" : "positive",
      "mood" : "good",
      "title" : "coc",
      "url" : "https://bihu.com/article/1649323677"
    } ],
    "score" : 3,
    "max" : 3
  },
  "place" : 19,
  "snapshot-date" : "2020-12-06T02:10:41.943Z"
}