{
  "bp-header" : {
    "owner" : "eosrealbpcsg",
    "total_votes" : "366759834258701.56250000000000000",
    "producer_key" : "EOS6fcpQu16GAASdLwK6BbTQTMK5EZSh1ecci2oKQJdioQvxp8DRs",
    "is_active" : 1,
    "url" : "http://www.eosreal.com",
    "unpaid_blocks" : 0,
    "last_claim_time" : "1970-01-01T00:00:00.000",
    "location" : 0,
    "prepared-url" : "http://www.eosreal.com"
  },
  "bp-json-summary" : {
    "read-error" : "read:'http://www.eosreal.com/bp.json': Unexpected character ('<' (code 60)): expected a valid value (number, String, array, object, 'true', 'false' or 'null')\n at [Source: (StringReader); line: 1, column: 2]",
    "url" : "http://www.eosreal.com/bp.json"
  },
  "analyzed-urls" : {
    "duplicate-urls" : null,
    "social-links" : [ ],
    "popularity-boosters" : [ ]
  },
  "p-ram-amounts" : [ ],
  "vote-percentage" : 2.682096392131885E-6,
  "scoring" : {
    "comp" : [ {
      "score" : "positive",
      "mood" : "good",
      "title" : "web",
      "url" : "http://www.eosreal.com"
    }, {
      "title" : "bp-json-err",
      "mood" : "warn",
      "url" : "http://www.eosreal.com/bp.json",
      "paragraphs" : [ "bp-json-invalid" ],
      "error" : "read:'http://www.eosreal.com/bp.json': Unexpected character ('<' (code 60)): expected a valid value (number, String, array, object, 'true', 'false' or 'null')\n at [Source: (StringReader); line: 1, column: 2]"
    }, {
      "mood" : "warn",
      "title" : "cant-load-coc",
      "paragraphs" : [ "p-cant-load-bp-json" ]
    } ],
    "score" : 1,
    "max" : 3
  },
  "place" : 127,
  "snapshot-date" : "2020-07-17T01:09:28.383Z"
}