{
  "bp-header" : {
    "owner" : "globalappdac",
    "total_votes" : "1646540716659.40356445312500000",
    "producer_key" : "EOS8B5HUoLWpnyBY4nWP4VZBehJi2zurFP7dSvYVGSoJbqsTiWokm",
    "is_active" : 1,
    "url" : "",
    "unpaid_blocks" : 0,
    "last_claim_time" : "2019-03-27T05:13:50.500",
    "location" : 584,
    "prepared-url" : null
  },
  "bp-json-summary" : null,
  "analyzed-urls" : {
    "duplicate-urls" : null,
    "social-links" : [ ],
    "popularity-boosters" : [ ]
  },
  "p-ram-amounts" : [ ],
  "vote-percentage" : 7.303983989515565E-9,
  "scoring" : {
    "comp" : [ {
      "title" : "no-web",
      "mood" : "bad",
      "paragraphs" : [ "value-empty" ]
    }, {
      "title" : "no-bp-json-url",
      "mood" : "bad",
      "paragraphs" : [ "value-empty" ]
    }, {
      "title" : "no-coc",
      "mood" : "bad",
      "paragraphs" : [ "value-empty" ]
    } ],
    "score" : 0,
    "max" : 3
  },
  "place" : 412,
  "snapshot-date" : "2020-11-20T02:13:22.407Z"
}