{
  "bp-header" : {
    "owner" : "gu2tembqgage",
    "total_votes" : "14905100307360.39453125000000000",
    "producer_key" : "EOS8BgJoo6XH7JKv8bmAwYNUoSAviBRVNpoUDJzG3Vz3DBi1zgnVf",
    "is_active" : 1,
    "url" : "https://www.cardano.org",
    "unpaid_blocks" : 0,
    "last_claim_time" : "1970-01-01T00:00:00.000",
    "location" : 0,
    "prepared-url" : "https://www.cardano.org"
  },
  "bp-json-summary" : {
    "dl-error" : "clj-http: status 404",
    "url" : "https://www.cardano.org/bp.json"
  },
  "analyzed-urls" : {
    "relative-links-count" : 22,
    "duplicate-urls" : null,
    "social-links" : [ "https://t.me/CardanoAnnouncements", "https://twitter.com/Cardano", "https://twitter.com/cardano", "https://www.facebook.com/groups/CardanoCommunity", "https://www.linkedin.com/company/cardano-foundation ", "https://www.meetup.com/en-AU/pro/cardano/", "https://www.reddit.com/r/cardano/", "https://www.youtube.com/channel/UCbQ9vGfezru1YRI1zDCtTGg" ],
    "social-links-count" : 8,
    "popularity-boosters" : [ "https://cardanofoundation.org/en/news/cardano-elevates-its-branding-ahead-of-smart-contract-roll-out-en/", "https://cardanofoundation.org/en/news/cardano-foundation-appoints-frederik-gregaard-as-ceo-and-strengthens-its-executive-leadership/", "https://cardanofoundation.org/en/news/flipside-cryptos-data-co-op-and-real-time-chainwalking%E2%84%A2-brings-superior-on-chain-visibility-to-cardano/", "https://cardanofoundation.org/en/privacy", "https://cardanofoundation.org/en/terms-and-conditions", "https://docs.cardano.org/", "https://forum.cardano.org/", "https://iohk.io/en/blog/posts/2020/08/05/philosophy-of-governance/" ],
    "popularity-boosters-count" : 8
  },
  "p-ram-amounts" : [ ],
  "vote-percentage" : 9.909182352044197E-8,
  "scoring" : {
    "comp" : [ {
      "score" : "positive",
      "mood" : "good",
      "title" : "web",
      "url" : "https://www.cardano.org"
    }, {
      "title" : "bp-json-err",
      "mood" : "warn",
      "url" : "https://www.cardano.org/bp.json",
      "paragraphs" : [ "bp-json-policy" ],
      "error" : "clj-http: status 404"
    }, {
      "mood" : "warn",
      "title" : "cant-load-coc",
      "paragraphs" : [ "p-cant-load-bp-json" ]
    } ],
    "score" : 1,
    "max" : 3
  },
  "place" : 248,
  "snapshot-date" : "2020-09-23T01:10:49.443Z"
}