{
  "bp-header" : {
    "owner" : "haydinjsgage",
    "total_votes" : "12807288809.03906250000000000",
    "producer_key" : "EOS7iKSaUs4vK5gE5sexXw1idtjNXzjRBuR1UjHUPRPxoUTQihqB7",
    "is_active" : 1,
    "url" : "",
    "unpaid_blocks" : 0,
    "last_claim_time" : "1970-01-01T00:00:00.000",
    "location" : 0,
    "prepared-url" : null
  },
  "bp-json-summary" : null,
  "analyzed-urls" : {
    "duplicate-urls" : null,
    "social-links" : [ ],
    "popularity-boosters" : [ ]
  },
  "p-ram-amounts" : [ ],
  "vote-percentage" : 1.2669863956276386E-10,
  "scoring" : {
    "comp" : [ {
      "title" : "no-web",
      "mood" : "bad",
      "paragraphs" : [ "value-empty" ]
    }, {
      "title" : "no-bp-json-url",
      "mood" : "bad",
      "paragraphs" : [ "value-empty" ]
    }, {
      "title" : "no-coc",
      "mood" : "bad",
      "paragraphs" : [ "value-empty" ]
    } ],
    "score" : 0,
    "max" : 3
  },
  "place" : 518,
  "snapshot-date" : "2019-10-08T01:17:31.753Z"
}