{
  "bp-header" : {
    "owner" : "haydinjxgige",
    "total_votes" : "1719664639999.99804687500000000",
    "producer_key" : "EOS5uGWGP6VWPwVFJWhu8NTx9cWSrufUhuNxWGu9z7pEovvR6kuT3",
    "is_active" : 1,
    "url" : "",
    "unpaid_blocks" : 0,
    "last_claim_time" : "1970-01-01T00:00:00.000",
    "location" : 0,
    "prepared-url" : null
  },
  "bp-json-summary" : null,
  "analyzed-urls" : {
    "duplicate-urls" : null,
    "social-links" : [ ],
    "popularity-boosters" : [ ]
  },
  "p-ram-amounts" : [ ],
  "vote-percentage" : 6.344701577679164E-9,
  "scoring" : {
    "comp" : [ {
      "title" : "no-web",
      "mood" : "bad",
      "paragraphs" : [ "value-empty" ]
    }, {
      "title" : "no-bp-json-url",
      "mood" : "bad",
      "paragraphs" : [ "value-empty" ]
    }, {
      "title" : "no-coc",
      "mood" : "bad",
      "paragraphs" : [ "value-empty" ]
    } ],
    "score" : 0,
    "max" : 3
  },
  "place" : 417,
  "snapshot-date" : "2020-12-11T02:13:11.652Z"
}