[ {
  "place" : 58,
  "snapshot-date" : "2020-05-11T01:07:58.348Z",
  "score" : 3,
  "url" : "https://buildteam.io/",
  "owner" : "buildteameos"
}, {
  "place" : 44,
  "snapshot-date" : "2020-05-11T01:07:58.348Z",
  "score" : 3,
  "url" : "https://uae.eosarabia.net",
  "owner" : "eosarabianet"
}, {
  "place" : 109,
  "snapshot-date" : "2020-05-11T01:07:58.348Z",
  "score" : 3,
  "url" : "https://eosarabia.one",
  "owner" : "eosarabiaone"
}, {
  "place" : 26,
  "snapshot-date" : "2020-05-11T01:07:58.348Z",
  "score" : 3,
  "url" : "https://eosamsterdam.net",
  "owner" : "eosamsterdam"
}, {
  "place" : 28,
  "snapshot-date" : "2020-05-11T01:07:58.348Z",
  "score" : 3,
  "url" : "https://eoscanada.com",
  "owner" : "eoscanadacom"
}, {
  "place" : 19,
  "snapshot-date" : "2020-05-11T01:07:58.348Z",
  "score" : 3,
  "url" : "https://eosdac.io",
  "owner" : "eosdacserver"
}, {
  "place" : 50,
  "snapshot-date" : "2020-05-11T01:07:58.348Z",
  "score" : 3,
  "url" : "http://blockgenic.io",
  "owner" : "blockgenicbp"
}, {
  "place" : 24,
  "snapshot-date" : "2020-05-11T01:07:58.348Z",
  "score" : 3,
  "url" : "https://www.eosdublin.com",
  "owner" : "eosdublinwow"
}, {
  "place" : 31,
  "snapshot-date" : "2020-05-11T01:07:58.348Z",
  "score" : 3,
  "url" : "https://eosblocksmith.io",
  "owner" : "blocksmithio"
}, {
  "place" : 6,
  "snapshot-date" : "2020-05-11T01:07:58.348Z",
  "score" : 3,
  "url" : "https://www.eosasia.one/",
  "owner" : "eosasia11111"
}, {
  "place" : 1,
  "snapshot-date" : "2020-05-11T01:07:58.348Z",
  "score" : 3,
  "url" : "https://atticlab.net",
  "owner" : "atticlabeosb"
}, {
  "place" : 158,
  "snapshot-date" : "2020-05-11T01:07:58.348Z",
  "score" : 3,
  "url" : "http://atticlab.net/",
  "owner" : "atticlabeosp"
}, {
  "place" : 11,
  "snapshot-date" : "2020-05-11T01:07:58.348Z",
  "score" : 3,
  "url" : "https://www.genereos.io",
  "owner" : "aus1genereos"
}, {
  "place" : 136,
  "snapshot-date" : "2020-05-11T01:07:58.348Z",
  "score" : 3,
  "url" : "https://www.blokcrafters.com",
  "owner" : "blokcrafters"
}, {
  "place" : 0,
  "snapshot-date" : "2020-05-11T01:07:58.348Z",
  "score" : 3,
  "url" : "https://www.bitfinex.com",
  "owner" : "bitfinexeos1"
}, {
  "place" : 15,
  "snapshot-date" : "2020-05-11T01:07:58.348Z",
  "score" : 3,
  "url" : "https://www.alohaeos.com",
  "owner" : "alohaeosprod"
}, {
  "place" : 12,
  "snapshot-date" : "2020-05-11T01:07:58.348Z",
  "score" : 3,
  "url" : "https://www.eoscafeblock.com/",
  "owner" : "eoscafeblock"
}, {
  "place" : 36,
  "snapshot-date" : "2020-05-11T01:07:58.348Z",
  "score" : 3,
  "url" : "https://eos.barcelona",
  "owner" : "eosbarcelona"
}, {
  "place" : 37,
  "snapshot-date" : "2020-05-11T01:07:58.348Z",
  "score" : 3,
  "url" : "https://eos.chainrift.com",
  "owner" : "chainriftxxx"
}, {
  "place" : 17,
  "snapshot-date" : "2020-05-11T01:07:58.348Z",
  "score" : 3,
  "url" : "https://www.eos42.io",
  "owner" : "eos42freedom"
}, {
  "place" : 45,
  "snapshot-date" : "2020-05-11T01:07:58.348Z",
  "score" : 3,
  "url" : "https://dutcheos.io",
  "owner" : "dutcheosxxxx"
}, {
  "place" : 3,
  "snapshot-date" : "2020-05-11T01:07:58.348Z",
  "score" : 3,
  "url" : "https://eoscannon.io",
  "owner" : "eoscannonchn"
}, {
  "place" : 100,
  "snapshot-date" : "2020-05-11T01:07:58.348Z",
  "score" : 3,
  "url" : "https://www.eosathens.com/",
  "owner" : "eosathenscom"
}, {
  "place" : 48,
  "snapshot-date" : "2020-05-11T01:07:58.348Z",
  "score" : 3,
  "url" : "https://www.auroraeos.com/",
  "owner" : "auroraeoscom"
}, {
  "place" : 97,
  "snapshot-date" : "2020-05-11T01:07:58.348Z",
  "score" : 3,
  "url" : "https://www.ecac.io",
  "owner" : "eoscorecacbp"
}, {
  "place" : 29,
  "snapshot-date" : "2020-05-11T01:07:58.348Z",
  "score" : 3,
  "url" : "https://eos.fish",
  "owner" : "eos.fish"
}, {
  "place" : 63,
  "snapshot-date" : "2020-05-11T01:07:58.348Z",
  "score" : 3,
  "url" : "https://www.blockgenesys.com",
  "owner" : "blockgenesys"
}, {
  "place" : 9,
  "snapshot-date" : "2020-05-11T01:07:58.348Z",
  "score" : 3,
  "url" : "https://www.eosbeijing.one",
  "owner" : "eosbeijingbp"
}, {
  "place" : 85,
  "snapshot-date" : "2020-05-11T01:07:58.348Z",
  "score" : 3,
  "url" : "https://blockchainlab.me",
  "owner" : "bchainlabeos"
}, {
  "place" : 8,
  "snapshot-date" : "2020-05-11T01:07:58.348Z",
  "score" : 3,
  "url" : "https://eoscochain.io",
  "owner" : "cochainworld"
}, {
  "place" : 79,
  "snapshot-date" : "2020-05-11T01:07:58.348Z",
  "score" : 3,
  "url" : "http://can-play.ca",
  "owner" : "1teamcanada1"
}, {
  "place" : 13,
  "snapshot-date" : "2020-05-11T01:07:58.348Z",
  "score" : 3,
  "url" : "https://eosauthority.com",
  "owner" : "eosauthority"
}, {
  "place" : 14,
  "snapshot-date" : "2020-05-11T01:07:58.348Z",
  "score" : 3,
  "url" : "https://www.eosargentina.io",
  "owner" : "argentinaeos"
}, {
  "place" : 16,
  "snapshot-date" : "2020-05-11T01:07:58.348Z",
  "score" : 3,
  "url" : "https://bp.cypherglass.com",
  "owner" : "cypherglasss"
}, {
  "place" : 18,
  "snapshot-date" : "2020-05-11T01:07:58.348Z",
  "score" : 3,
  "url" : "https://cryptolions.io",
  "owner" : "cryptolions1"
}, {
  "place" : 30,
  "snapshot-date" : "2020-05-11T01:07:58.348Z",
  "score" : 3,
  "url" : "https://www.eosantpool.com",
  "owner" : "eosantpoolbp"
}, {
  "place" : 101,
  "snapshot-date" : "2020-05-11T01:07:58.348Z",
  "score" : 2,
  "url" : "https://www.bitportal.io",
  "owner" : "bp.bp"
}, {
  "place" : 42,
  "snapshot-date" : "2020-05-11T01:07:58.348Z",
  "score" : 2,
  "url" : "https://www.bitwires.com",
  "owner" : "bitwireeosbp"
}, {
  "place" : 33,
  "snapshot-date" : "2020-05-11T01:07:58.348Z",
  "score" : 2,
  "url" : "https://about.dpos.club",
  "owner" : "dposclubprod"
}, {
  "place" : 4,
  "snapshot-date" : "2020-05-11T01:07:58.348Z",
  "score" : 2,
  "url" : "https://www.blockpool.com",
  "owner" : "blockpooleos"
}, {
  "place" : 27,
  "snapshot-date" : "2020-05-11T01:07:58.348Z",
  "score" : 2,
  "url" : "https://eoscleaner.com",
  "owner" : "eoscleanerbp"
}, {
  "place" : 59,
  "snapshot-date" : "2020-05-11T01:07:58.348Z",
  "score" : 2,
  "url" : "http://blockpro.one/",
  "owner" : "blockpro1eos"
}, {
  "place" : 20,
  "snapshot-date" : "2020-05-11T01:07:58.348Z",
  "score" : 2,
  "url" : "https://ecoboost.app/",
  "owner" : "ecoboost1111"
}, {
  "place" : 2,
  "snapshot-date" : "2020-05-11T01:07:58.348Z",
  "score" : 2,
  "url" : "https://eos.big.one",
  "owner" : "big.one"
}, {
  "place" : 5,
  "snapshot-date" : "2020-05-11T01:07:58.348Z",
  "score" : 2,
  "url" : "https://eos.wiki",
  "owner" : "eosdotwikibp"
}, {
  "place" : 25,
  "snapshot-date" : "2020-05-11T01:07:58.348Z",
  "score" : 2,
  "url" : "http://athenbp.club",
  "owner" : "eosathenabp1"
}, {
  "place" : 34,
  "snapshot-date" : "2020-05-11T01:07:58.348Z",
  "score" : 2,
  "url" : "https://eoscostarica.io",
  "owner" : "costaricaeos"
}, {
  "place" : 74,
  "snapshot-date" : "2020-05-11T01:07:58.348Z",
  "score" : 2,
  "url" : "https://alexbond.keybase.pub",
  "owner" : "disfundbpeos"
}, {
  "place" : 77,
  "snapshot-date" : "2020-05-11T01:07:58.348Z",
  "score" : 2,
  "url" : "https://eos.bepal.io",
  "owner" : "eosbepalsafe"
}, {
  "place" : 84,
  "snapshot-date" : "2020-05-11T01:07:58.348Z",
  "score" : 2,
  "url" : "https://deneos_io.keybase.pub",
  "owner" : "deneosioblck"
}, {
  "place" : 119,
  "snapshot-date" : "2020-05-11T01:07:58.348Z",
  "score" : 2,
  "url" : "https://eoscity.io",
  "owner" : "eoscityioeos"
}, {
  "place" : 7,
  "snapshot-date" : "2020-05-11T01:07:58.348Z",
  "score" : 1,
  "url" : "https://www.binance.com",
  "owner" : "binancestake"
}, {
  "place" : 66,
  "snapshot-date" : "2020-05-11T01:07:58.348Z",
  "score" : 1,
  "url" : "https://cryptokylin.io",
  "owner" : "cryptokylin1"
}, {
  "place" : 111,
  "snapshot-date" : "2020-05-11T01:07:58.348Z",
  "score" : 1,
  "url" : "https://cobo.com",
  "owner" : "cobowalletbp"
}, {
  "place" : 87,
  "snapshot-date" : "2020-05-11T01:07:58.348Z",
  "score" : 1,
  "url" : "https://chain.pro",
  "owner" : "candyairdrop"
}, {
  "place" : 10,
  "snapshot-date" : "2020-05-11T01:07:58.348Z",
  "score" : 1,
  "url" : "https://certik.org",
  "owner" : "certikeosorg"
}, {
  "place" : 88,
  "snapshot-date" : "2020-05-11T01:07:58.348Z",
  "score" : 1,
  "url" : "http://www.infinitystones.io/eos",
  "owner" : "eosdanhuausa"
}, {
  "place" : 107,
  "snapshot-date" : "2020-05-11T01:07:58.348Z",
  "score" : 1,
  "url" : "http://bitcoineos.fun",
  "owner" : "bitcoineosfu"
}, {
  "place" : 144,
  "snapshot-date" : "2020-05-11T01:07:58.348Z",
  "score" : 1,
  "url" : "http://www.google.com",
  "owner" : "blackholebug"
}, {
  "place" : 46,
  "snapshot-date" : "2020-05-11T01:07:58.348Z",
  "score" : 1,
  "url" : "http://eosadd.com",
  "owner" : "eosadddddddd"
}, {
  "place" : 38,
  "snapshot-date" : "2020-05-11T01:07:58.348Z",
  "score" : 1,
  "url" : "http://www.dilidili.name",
  "owner" : "dilidilifans"
}, {
  "place" : 49,
  "snapshot-date" : "2020-05-11T01:07:58.348Z",
  "score" : 1,
  "url" : "https://candy.one/",
  "owner" : "eoscandyone1"
}, {
  "place" : 65,
  "snapshot-date" : "2020-05-11T01:07:58.348Z",
  "score" : 1,
  "url" : "https://bp.eosbean.com",
  "owner" : "eosbeaneosbp"
}, {
  "place" : 145,
  "snapshot-date" : "2020-05-11T01:07:58.348Z",
  "score" : 1,
  "url" : "http://eblock.io",
  "owner" : "chattleblock"
}, {
  "place" : 35,
  "snapshot-date" : "2020-05-11T01:07:58.348Z",
  "score" : 1,
  "url" : "https://blockmatrix.network",
  "owner" : "blockmatrix1"
}, {
  "place" : 43,
  "snapshot-date" : "2020-05-11T01:07:58.348Z",
  "score" : 1,
  "url" : "https://dapp.pub",
  "owner" : "dapppub.bp"
}, {
  "place" : 54,
  "snapshot-date" : "2020-05-11T01:07:58.348Z",
  "score" : 1,
  "url" : "https://eos.blckchnd.com",
  "owner" : "blockchained"
}, {
  "place" : 69,
  "snapshot-date" : "2020-05-11T01:07:58.348Z",
  "score" : 1,
  "url" : "http://btccpooleos.com",
  "owner" : "btccpooleos1"
}, {
  "place" : 72,
  "snapshot-date" : "2020-05-11T01:07:58.348Z",
  "score" : 1,
  "url" : "https://bp.eosindex.io",
  "owner" : "bpeosindexio"
}, {
  "place" : 75,
  "snapshot-date" : "2020-05-11T01:07:58.348Z",
  "score" : 1,
  "url" : "http://www.cocosbcx.io/",
  "owner" : "eoscocoshost"
}, {
  "place" : 86,
  "snapshot-date" : "2020-05-11T01:07:58.348Z",
  "score" : 1,
  "url" : "http://eos.college",
  "owner" : "eoscollegeus"
}, {
  "place" : 113,
  "snapshot-date" : "2020-05-11T01:07:58.348Z",
  "score" : 1,
  "url" : "http://eosteam.org/",
  "owner" : "eosdevteambp"
}, {
  "place" : 123,
  "snapshot-date" : "2020-05-11T01:07:58.348Z",
  "score" : 1,
  "url" : "http://www.divinerapier.com",
  "owner" : "divinerapier"
}, {
  "place" : 124,
  "snapshot-date" : "2020-05-11T01:07:58.348Z",
  "score" : 1,
  "url" : "http://eosteam.org/",
  "owner" : "bp.vip"
}, {
  "place" : 126,
  "snapshot-date" : "2020-05-11T01:07:58.348Z",
  "score" : 1,
  "url" : "http://www.test.com",
  "owner" : "cryptominers"
}, {
  "place" : 150,
  "snapshot-date" : "2020-05-11T01:07:58.348Z",
  "score" : 1,
  "url" : "https://cadeos.io",
  "owner" : "cadeosiocode"
}, {
  "place" : 21,
  "snapshot-date" : "2020-05-11T01:07:58.348Z",
  "score" : 0,
  "url" : "https://acroeos.one",
  "owner" : "acroeos12345"
}, {
  "place" : 22,
  "snapshot-date" : "2020-05-11T01:07:58.348Z",
  "score" : 0,
  "url" : "https://en.eosbixin.com",
  "owner" : "eosbixinboot"
}, {
  "place" : 23,
  "snapshot-date" : "2020-05-11T01:07:58.348Z",
  "score" : 0,
  "url" : "https://dexeos.io",
  "owner" : "dexeosbpnode"
}, {
  "place" : 32,
  "snapshot-date" : "2020-05-11T01:07:58.348Z",
  "score" : 0,
  "url" : "https://eoseco.com",
  "owner" : "eosecoeoseco"
}, {
  "place" : 39,
  "snapshot-date" : "2020-05-11T01:07:58.348Z",
  "score" : 0,
  "url" : "https://www.eosio.africa",
  "owner" : "eosafricaone"
}, {
  "place" : 40,
  "snapshot-date" : "2020-05-11T01:07:58.348Z",
  "score" : 0,
  "url" : "https://eos.bitspace.no",
  "owner" : "bitspacenode"
}, {
  "place" : 41,
  "snapshot-date" : "2020-05-11T01:07:58.348Z",
  "score" : 0,
  "url" : "https://eos.cybex.io/",
  "owner" : "eoscybexiobp"
}, {
  "place" : 47,
  "snapshot-date" : "2020-05-11T01:07:58.348Z",
  "score" : 0,
  "url" : "http://eos.vote",
  "owner" : "123singapore"
}, {
  "place" : 51,
  "snapshot-date" : "2020-05-11T01:07:58.348Z",
  "score" : 0,
  "url" : "https://blockeos.io",
  "owner" : "blockeosioio"
}, {
  "place" : 52,
  "snapshot-date" : "2020-05-11T01:07:58.348Z",
  "score" : 0,
  "url" : "https://bp2.io",
  "owner" : "bp2bp2bp2bp2"
}, {
  "place" : 53,
  "snapshot-date" : "2020-05-11T01:07:58.348Z",
  "score" : 0,
  "url" : "https://bpac.io",
  "owner" : "bpacbpacbpac"
}, {
  "place" : 55,
  "snapshot-date" : "2020-05-11T01:07:58.348Z",
  "score" : 0,
  "url" : "https://eostheworld.io",
  "owner" : "1eostheworld"
}, {
  "place" : 56,
  "snapshot-date" : "2020-05-11T01:07:58.348Z",
  "score" : 0,
  "url" : null,
  "owner" : "bpkhmereoskh"
}, {
  "place" : 57,
  "snapshot-date" : "2020-05-11T01:07:58.348Z",
  "score" : 0,
  "url" : "https://eosemerge.io",
  "owner" : "emergepoland"
}, {
  "place" : 60,
  "snapshot-date" : "2020-05-11T01:07:58.348Z",
  "score" : 0,
  "url" : "http://eoscube.io/",
  "owner" : "eoscube11111"
}, {
  "place" : 61,
  "snapshot-date" : "2020-05-11T01:07:58.348Z",
  "score" : 0,
  "url" : "https://www.activeeos.com",
  "owner" : "activeeoscom"
}, {
  "place" : 62,
  "snapshot-date" : "2020-05-11T01:07:58.348Z",
  "score" : 0,
  "url" : null,
  "owner" : "eoschaintech"
}, {
  "place" : 64,
  "snapshot-date" : "2020-05-11T01:07:58.348Z",
  "score" : 0,
  "url" : "https://cypherblock.io",
  "owner" : "cypherblocks"
}, {
  "place" : 67,
  "snapshot-date" : "2020-05-11T01:07:58.348Z",
  "score" : 0,
  "url" : "http://www.daoeos.io",
  "owner" : "daoeosbpbwin"
}, {
  "place" : 68,
  "snapshot-date" : "2020-05-11T01:07:58.348Z",
  "score" : 0,
  "url" : "http://eos121dac.io/",
  "owner" : "eos121wallet"
}, {
  "place" : 70,
  "snapshot-date" : "2020-05-11T01:07:58.348Z",
  "score" : 0,
  "url" : "http://www.eosamericas.com",
  "owner" : "eosamericas2"
}, {
  "place" : 71,
  "snapshot-date" : "2020-05-11T01:07:58.348Z",
  "score" : 0,
  "url" : "http://eosio.university/",
  "owner" : "chainclubeos"
}, {
  "place" : 73,
  "snapshot-date" : "2020-05-11T01:07:58.348Z",
  "score" : 0,
  "url" : "https://eos.csx.io",
  "owner" : "csxcommunity"
}, {
  "place" : 76,
  "snapshot-date" : "2020-05-11T01:07:58.348Z",
  "score" : 0,
  "url" : "https://eosbelarus.com",
  "owner" : "eosbelarusio"
}, {
  "place" : 78,
  "snapshot-date" : "2020-05-11T01:07:58.348Z",
  "score" : 0,
  "url" : null,
  "owner" : "eosastrology"
}, {
  "place" : 80,
  "snapshot-date" : "2020-05-11T01:07:58.348Z",
  "score" : 0,
  "url" : "https://www.eoseafrica.io",
  "owner" : "eoseafricabp"
}, {
  "place" : 81,
  "snapshot-date" : "2020-05-11T01:07:58.348Z",
  "score" : 0,
  "url" : null,
  "owner" : "eosbutterfly"
}, {
  "place" : 82,
  "snapshot-date" : "2020-05-11T01:07:58.348Z",
  "score" : 0,
  "url" : "https://bpnode.com",
  "owner" : "bpnodecanada"
}, {
  "place" : 83,
  "snapshot-date" : "2020-05-11T01:07:58.348Z",
  "score" : 0,
  "url" : null,
  "owner" : "eoschaindata"
}, {
  "place" : 89,
  "snapshot-date" : "2020-05-11T01:07:58.348Z",
  "score" : 0,
  "url" : "https://www.genereos-sydney.io/",
  "owner" : "eosaustralia"
}, {
  "place" : 90,
  "snapshot-date" : "2020-05-11T01:07:58.348Z",
  "score" : 0,
  "url" : "https://eos.block.cc/",
  "owner" : "blockcceosio"
}, {
  "place" : 91,
  "snapshot-date" : "2020-05-11T01:07:58.348Z",
  "score" : 0,
  "url" : "https://eosarmy.io",
  "owner" : "eosarmyioant"
}, {
  "place" : 92,
  "snapshot-date" : "2020-05-11T01:07:58.348Z",
  "score" : 0,
  "url" : "http://eosblockzero.com",
  "owner" : "eosblockzero"
}, {
  "place" : 93,
  "snapshot-date" : "2020-05-11T01:07:58.348Z",
  "score" : 0,
  "url" : "https://eos.bitcoingod.org/",
  "owner" : "bitcoingod11"
}, {
  "place" : 94,
  "snapshot-date" : "2020-05-11T01:07:58.348Z",
  "score" : 0,
  "url" : null,
  "owner" : "eosdailynews"
}, {
  "place" : 95,
  "snapshot-date" : "2020-05-11T01:07:58.348Z",
  "score" : 0,
  "url" : null,
  "owner" : "eosclockwise"
}, {
  "place" : 96,
  "snapshot-date" : "2020-05-11T01:07:58.348Z",
  "score" : 0,
  "url" : null,
  "owner" : "eosbattlenet"
}, {
  "place" : 98,
  "snapshot-date" : "2020-05-11T01:07:58.348Z",
  "score" : 0,
  "url" : "https://www.eosdusseldorf.de",
  "owner" : "dusseldorfde"
}, {
  "place" : 99,
  "snapshot-date" : "2020-05-11T01:07:58.348Z",
  "score" : 0,
  "url" : null,
  "owner" : "eoscrowdsale"
}, {
  "place" : 102,
  "snapshot-date" : "2020-05-11T01:07:58.348Z",
  "score" : 0,
  "url" : null,
  "owner" : "eosdelivered"
}, {
  "place" : 103,
  "snapshot-date" : "2020-05-11T01:07:58.348Z",
  "score" : 0,
  "url" : null,
  "owner" : "eosdirectory"
}, {
  "place" : 104,
  "snapshot-date" : "2020-05-11T01:07:58.348Z",
  "score" : 0,
  "url" : null,
  "owner" : "eoschristian"
}, {
  "place" : 105,
  "snapshot-date" : "2020-05-11T01:07:58.348Z",
  "score" : 0,
  "url" : "https://blockmachine.io",
  "owner" : "blockmachin3"
}, {
  "place" : 106,
  "snapshot-date" : "2020-05-11T01:07:58.348Z",
  "score" : 0,
  "url" : "https://bluchain.tech",
  "owner" : "eosbluchain1"
}, {
  "place" : 108,
  "snapshot-date" : "2020-05-11T01:07:58.348Z",
  "score" : 0,
  "url" : "http://Malta",
  "owner" : "accproxsomes"
}, {
  "place" : 110,
  "snapshot-date" : "2020-05-11T01:07:58.348Z",
  "score" : 0,
  "url" : "https://eosuperman.io",
  "owner" : "cointelegrph"
}, {
  "place" : 112,
  "snapshot-date" : "2020-05-11T01:07:58.348Z",
  "score" : 0,
  "url" : "http://eosblocktree.io",
  "owner" : "eosblocktree"
}, {
  "place" : 114,
  "snapshot-date" : "2020-05-11T01:07:58.348Z",
  "score" : 0,
  "url" : null,
  "owner" : "eos2bcuworld"
}, {
  "place" : 115,
  "snapshot-date" : "2020-05-11T01:07:58.348Z",
  "score" : 0,
  "url" : "http://www.aibilink.com",
  "owner" : "eoschainbmok"
}, {
  "place" : 116,
  "snapshot-date" : "2020-05-11T01:07:58.348Z",
  "score" : 0,
  "url" : "https://eos.blockroad.co",
  "owner" : "blockroadger"
}, {
  "place" : 117,
  "snapshot-date" : "2020-05-11T01:07:58.348Z",
  "score" : 0,
  "url" : null,
  "owner" : "biconomypool"
}, {
  "place" : 118,
  "snapshot-date" : "2020-05-11T01:07:58.348Z",
  "score" : 0,
  "url" : "https://www.blockinsider.info/",
  "owner" : "blockinsider"
}, {
  "place" : 120,
  "snapshot-date" : "2020-05-11T01:07:58.348Z",
  "score" : 0,
  "url" : "https://eosbestbp.io",
  "owner" : "eosbestbpio1"
}, {
  "place" : 121,
  "snapshot-date" : "2020-05-11T01:07:58.348Z",
  "score" : 0,
  "url" : "https://www.acgeos.com",
  "owner" : "acgeoscomeos"
}, {
  "place" : 122,
  "snapshot-date" : "2020-05-11T01:07:58.348Z",
  "score" : 0,
  "url" : "https://india.com",
  "owner" : "111112222244"
}, {
  "place" : 125,
  "snapshot-date" : "2020-05-11T01:07:58.348Z",
  "score" : 0,
  "url" : "https://eosclan.dev",
  "owner" : "eosclan.x"
}, {
  "place" : 127,
  "snapshot-date" : "2020-05-11T01:07:58.348Z",
  "score" : 0,
  "url" : "http://eosnode.daketech.net",
  "owner" : "blueoceanam1"
}, {
  "place" : 128,
  "snapshot-date" : "2020-05-11T01:07:58.348Z",
  "score" : 0,
  "url" : null,
  "owner" : "chinajsycbjy"
}, {
  "place" : 129,
  "snapshot-date" : "2020-05-11T01:07:58.348Z",
  "score" : 0,
  "url" : "http://berryofmyeye.io",
  "owner" : "berryofmyeye"
}, {
  "place" : 130,
  "snapshot-date" : "2020-05-11T01:07:58.348Z",
  "score" : 0,
  "url" : "http://eosbattles.com",
  "owner" : "1eosbattles1"
}, {
  "place" : 131,
  "snapshot-date" : "2020-05-11T01:07:58.348Z",
  "score" : 0,
  "url" : "https://india.com",
  "owner" : "111112222255"
}, {
  "place" : 132,
  "snapshot-date" : "2020-05-11T01:07:58.348Z",
  "score" : 0,
  "url" : null,
  "owner" : "btctothemoon"
}, {
  "place" : 133,
  "snapshot-date" : "2020-05-11T01:07:58.348Z",
  "score" : 0,
  "url" : null,
  "owner" : "appincubator"
}, {
  "place" : 134,
  "snapshot-date" : "2020-05-11T01:07:58.348Z",
  "score" : 0,
  "url" : null,
  "owner" : "eeeeeeostest"
}, {
  "place" : 135,
  "snapshot-date" : "2020-05-11T01:07:58.348Z",
  "score" : 0,
  "url" : "https://dappsmeister.io",
  "owner" : "dappsmeister"
}, {
  "place" : 137,
  "snapshot-date" : "2020-05-11T01:07:58.348Z",
  "score" : 0,
  "url" : null,
  "owner" : "adshaoadshao"
}, {
  "place" : 138,
  "snapshot-date" : "2020-05-11T01:07:58.348Z",
  "score" : 0,
  "url" : null,
  "owner" : "bitwala.bank"
}, {
  "place" : 139,
  "snapshot-date" : "2020-05-11T01:07:58.348Z",
  "score" : 0,
  "url" : "https://eos.eclipse24.io",
  "owner" : "eoseclipse24"
}, {
  "place" : 140,
  "snapshot-date" : "2020-05-11T01:07:58.348Z",
  "score" : 0,
  "url" : null,
  "owner" : "eosdlbpservr"
}, {
  "place" : 141,
  "snapshot-date" : "2020-05-11T01:07:58.348Z",
  "score" : 0,
  "url" : null,
  "owner" : "ashutoken123"
}, {
  "place" : 142,
  "snapshot-date" : "2020-05-11T01:07:58.348Z",
  "score" : 0,
  "url" : null,
  "owner" : "dazieos55555"
}, {
  "place" : 143,
  "snapshot-date" : "2020-05-11T01:07:58.348Z",
  "score" : 0,
  "url" : "https://bptomoon.io",
  "owner" : "bptothemoon1"
}, {
  "place" : 146,
  "snapshot-date" : "2020-05-11T01:07:58.348Z",
  "score" : 0,
  "url" : "http://agjcoin.com",
  "owner" : "agj4navercom"
}, {
  "place" : 147,
  "snapshot-date" : "2020-05-11T01:07:58.348Z",
  "score" : 0,
  "url" : "https://cryptopacific.keybase.pub/",
  "owner" : "eosalpineski"
}, {
  "place" : 148,
  "snapshot-date" : "2020-05-11T01:07:58.348Z",
  "score" : 0,
  "url" : null,
  "owner" : "cloudwallet1"
}, {
  "place" : 149,
  "snapshot-date" : "2020-05-11T01:07:58.348Z",
  "score" : 0,
  "url" : null,
  "owner" : "dukeqwertyui"
}, {
  "place" : 151,
  "snapshot-date" : "2020-05-11T01:07:58.348Z",
  "score" : 0,
  "url" : "https://chain.ga",
  "owner" : "asmallpotato"
}, {
  "place" : 152,
  "snapshot-date" : "2020-05-11T01:07:58.348Z",
  "score" : 0,
  "url" : "https://chain.gam",
  "owner" : "1smallpotato"
}, {
  "place" : 153,
  "snapshot-date" : "2020-05-11T01:07:58.348Z",
  "score" : 0,
  "url" : null,
  "owner" : "caokunkevin1"
}, {
  "place" : 154,
  "snapshot-date" : "2020-05-11T01:07:58.348Z",
  "score" : 0,
  "url" : null,
  "owner" : "andryha2yha1"
}, {
  "place" : 155,
  "snapshot-date" : "2020-05-11T01:07:58.348Z",
  "score" : 0,
  "url" : "https://eosdublin.com",
  "owner" : "eosdublin.m"
}, {
  "place" : 156,
  "snapshot-date" : "2020-05-11T01:07:58.348Z",
  "score" : 0,
  "url" : null,
  "owner" : "chigago.bank"
}, {
  "place" : 157,
  "snapshot-date" : "2020-05-11T01:07:58.348Z",
  "score" : 0,
  "url" : "https://eospublic.chainrift.com",
  "owner" : "chainriftbp1"
} ]