{
  "bp-header" : {
    "owner" : "mathsssnodes",
    "total_votes" : "8334230211.31475639343261719",
    "producer_key" : "EOS5HNQ3a3fYaoKf3mEzZV2zDgiRE7EQ6DZjZUgqSXv483N38H5FW",
    "is_active" : 1,
    "url" : "https://mathwallet.org",
    "unpaid_blocks" : 0,
    "last_claim_time" : "2019-07-11T08:50:28.000",
    "location" : 156,
    "prepared-url" : "https://mathwallet.org"
  },
  "bp-json-summary" : {
    "dl-error" : "clj-http: status 404",
    "url" : "https://mathwallet.org/bp.json"
  },
  "analyzed-urls" : {
    "relative-links-count" : 32,
    "duplicate-urls" : null,
    "social-links" : [ "https://github.com/mathwallet", "https://t.me/mathwalletCN", "https://weibo.com/2803855662/" ],
    "social-links-count" : 3,
    "popularity-boosters" : [ "http://blog.mathwallet.net/?p=1676", "http://blog.mathwallet.net/?p=1707", "http://blog.mathwallet.net/?p=2320", "http://blog.mathwallet.net/?p=2327", "http://blog.mathwallet.net/?p=2330", "http://blog.mathwallet.net/?page_id=1889", "http://bnb48.club/", "http://eosgravity.com/", "http://lianyuyu.com/", "http://www.lianjinshu.com/", "https://atlasp.io/", "https://chain.pro/", "https://chrome.google.com/webstore/detail/math-wallet/afbcbjpbpfadlkmhmclhkeeodmamcflc", "https://dapp.review/explore", "https://delphy.org/", "https://dgoods.org/", "https://eospark.com/", "https://ext.se.360.cn/webstore/detail/afbcbjpbpfadlkmhmclhkeeodmamcflc", "https://fio.foundation/", "https://imeos.one/", "https://itunes.apple.com/us/app/math-blockchain-wallet/id1383637331?l=zh&ls=1&mt=8", "https://m.maiziqianbao.net/eth/submitNewDapp", "https://m.maiziqianbao.net/eth/submitNewToken?type=", "https://m.maiziqianbao.net/vpos", "https://mathdapp.store", "https://medishares-cn.oss-cn-hangzhou.aliyuncs.com/android-apk/alpha/mathwallet_android.apk?r=", "https://morecoin.com/", "https://newdex.io/", "https://play.google.com/store/apps/details?id=com.medishares.android", "https://testflight.apple.com", "https://testflight.apple.com/join/LJ4utJAW", "https://weidian.com/item.html?itemID=235747398620902415380&spider_token=061c", "https://www.qkl123.com/", "https://www.spider.store/", "https://www.thorswap.com/", "https://ydapp.io/" ],
    "popularity-boosters-count" : 36
  },
  "p-ram-amounts" : [ ],
  "vote-percentage" : 6.909990839908108E-11,
  "scoring" : {
    "comp" : [ {
      "score" : "positive",
      "mood" : "good",
      "title" : "web",
      "url" : "https://mathwallet.org"
    }, {
      "title" : "bp-json-err",
      "mood" : "warn",
      "url" : "https://mathwallet.org/bp.json",
      "paragraphs" : [ "bp-json-policy" ],
      "error" : "clj-http: status 404"
    }, {
      "mood" : "warn",
      "title" : "cant-load-coc",
      "paragraphs" : [ "p-cant-load-bp-json" ]
    } ],
    "score" : 1,
    "max" : 3
  },
  "place" : 525,
  "snapshot-date" : "2019-12-11T02:12:11.246Z"
}